gitprovenance.py
gitprovenance-0.0.2.dist-info/LICENSE.rst
gitprovenance-0.0.2.dist-info/WHEEL
gitprovenance-0.0.2.dist-info/METADATA
gitprovenance-0.0.2.dist-info/RECORD
