Metadata-Version: 2.1
Name: gitprovenance
Version: 0.0.2
Summary: gitprovenance
Home-page: https://github.com/pv/gitprovenance/
License: UNKNOWN
Author: Pauli Virtanen
Author-email: pav@iki.fi
Requires-Python: >=3.5
Classifier: License :: OSI Approved :: BSD License
Classifier: Programming Language :: Python :: 3
